pyhuman/__init__.py
pyhuman-0.0.1.dist-info/LICENSE
pyhuman-0.0.1.dist-info/METADATA
pyhuman-0.0.1.dist-info/WHEEL
pyhuman-0.0.1.dist-info/top_level.txt
pyhuman-0.0.1.dist-info/RECORD
