Metadata-Version: 2.1
Name: pyhuman
Version: 0.0.1
Summary: 3D Human Model in Python
Home-page: https://github.com/quanhua92/pyhuman
Author: Quan Hua
Author-email: quanhua92@gmail.com
License: Apache
Platform: UNKNOWN
Classifier: License :: OSI Approved :: Apache Software License
Classifier: Programming Language :: Python :: 3
Classifier: Programming Language :: Python :: 3.7
